README.md
setup.py
linkedin_message_scraper_bot/__init__.py
linkedin_message_scraper_bot.egg-info/PKG-INFO
linkedin_message_scraper_bot.egg-info/SOURCES.txt
linkedin_message_scraper_bot.egg-info/dependency_links.txt
linkedin_message_scraper_bot.egg-info/requires.txt
linkedin_message_scraper_bot.egg-info/top_level.txt