Metadata-Version: 2.1
Name: linkedin-message-scraper-bot
Version: 1.0.0
Summary: A python library to scrape user's messages data from linkedin automatically.
Home-page: https://linkedin-api.datakund.com/en/latest/
Author: DataKund
Author-email: datakund@gmail.com
License: Apache License 2.0
Keywords: linkedin python bot_studio scraper messages user-messages data web-scraping
Platform: UNKNOWN
